deropy/__init__.py
deropy/logger.py
deropy/main.py
deropy/test_utils.py
deropy/utils.py
deropy/commands/__init__.py
deropy/commands/configure.py
deropy/commands/deploy.py
deropy/commands/generate.py
deropy/commands/simulate.py
deropy/commands/transpile.py
deropy/dvm/Smartcontract.py
deropy/dvm/__init__.py
deropy/dvm/parser.py
deropy/dvm/tester.py
deropy/dvm/utils.py
deropy/dvm/dast/__init__.py
deropy/dvm/dast/argument.py
deropy/dvm/dast/assignement.py
deropy/dvm/dast/binaryOperator.py
deropy/dvm/dast/comment.py
deropy/dvm/dast/compare.py
deropy/dvm/dast/constant.py
deropy/dvm/dast/dast_converter.py
deropy/dvm/dast/declaration.py
deropy/dvm/dast/functionCall.py
deropy/dvm/dast/functionDef.py
deropy/dvm/dast/goto.py
deropy/dvm/dast/ifTest.py
deropy/dvm/dast/name.py
deropy/dvm/dast/operator.py
deropy/dvm/dast/returns.py
deropy/dvm/dast/variableDeclarationAdnAssignement.py
deropy/dvm/dast/whileLoop.py
deropy/dvm/functions/AddressRaw.py
deropy/dvm/functions/AddressString.py
deropy/dvm/functions/AssetValue.py
deropy/dvm/functions/Atoi.py
deropy/dvm/functions/Blid.py
deropy/dvm/functions/BlockHeight.py
deropy/dvm/functions/BlockTimestamp.py
deropy/dvm/functions/Delete.py
deropy/dvm/functions/Dero.py
deropy/dvm/functions/DeroValue.py
deropy/dvm/functions/Exists.py
deropy/dvm/functions/Function.py
deropy/dvm/functions/Hex.py
deropy/dvm/functions/HexDecode.py
deropy/dvm/functions/IsAddressValid.py
deropy/dvm/functions/Itoa.py
deropy/dvm/functions/Keccak256.py
deropy/dvm/functions/Load.py
deropy/dvm/functions/MapDelete.py
deropy/dvm/functions/MapExists.py
deropy/dvm/functions/MapGet.py
deropy/dvm/functions/MapStore.py
deropy/dvm/functions/Panic.py
deropy/dvm/functions/Random.py
deropy/dvm/functions/Scid.py
deropy/dvm/functions/SendAssetToAddress.py
deropy/dvm/functions/SendDeroToAddress.py
deropy/dvm/functions/Sha256.py
deropy/dvm/functions/Sha3256.py
deropy/dvm/functions/Signer.py
deropy/dvm/functions/Store.py
deropy/dvm/functions/Strlen.py
deropy/dvm/functions/Substr.py
deropy-0.3.0.dist-info/LICENSE
deropy-0.3.0.dist-info/METADATA
deropy-0.3.0.dist-info/WHEEL
deropy-0.3.0.dist-info/entry_points.txt
deropy-0.3.0.dist-info/top_level.txt
deropy-0.3.0.dist-info/RECORD
