Metadata-Version: 2.1
Name: deropy
Version: 0.3.0
Summary: A set of tool to help of DERO smart contract development
Home-page: https://github.com/dero-hyperbolic/deropy.git
Author-email: leocances@gmail.com
Classifier: Programming Language :: Python :: 3
Classifier: Operating System :: OS Independent
License-File: LICENSE
Requires-Dist: click ==8.0.4
Requires-Dist: requests ==2.31.0
Requires-Dist: coloredlogs ==15.0.1
Requires-Dist: pyperclip ==1.8.2
Requires-Dist: python-dotenv ==0.20.0
Requires-Dist: InquirerPy ==0.3.4
Requires-Dist: pycryptodome ==3.20.0
